openhumans/__init__.py
openhumans/admin.py
openhumans/apps.py
openhumans/exceptions.py
openhumans/helpers.py
openhumans/models.py
openhumans/receivers.py
openhumans/settings.py
openhumans/signals.py
openhumans/urls.py
openhumans/views.py
openhumans/migrations/0001_initial.py
openhumans/migrations/0002_openhumansmember_oh_deauth.py
openhumans/migrations/__init__.py
openhumans/tests/__init__.py
openhumans/tests/tests.py
openhumans/tests/tests_models.py
django_open_humans-0.2.0.dist-info/LICENSE
django_open_humans-0.2.0.dist-info/METADATA
django_open_humans-0.2.0.dist-info/WHEEL
django_open_humans-0.2.0.dist-info/top_level.txt
django_open_humans-0.2.0.dist-info/RECORD
