Metadata-Version: 2.1
Name: django-open-humans
Version: 0.2.0
Summary: Django module for interacting with Open Humans
Home-page: https://github.com/OpenHumans/django-open-humans
Author: Open Humans
Author-email: support@openhumans.org
License: MIT
Keywords: open humans,openhumans
Classifier: Development Status :: 3 - Alpha
Classifier: Environment :: Web Environment
Classifier: Framework :: Django
Classifier: Intended Audience :: Developers
Classifier: Intended Audience :: Information Technology
Classifier: Intended Audience :: System Administrators
Classifier: License :: OSI Approved :: MIT License
Classifier: Programming Language :: Python
Classifier: Topic :: Utilities
Classifier: Topic :: Internet :: WWW/HTTP
License-File: LICENSE
Requires-Dist: open-humans-api >=0.2.4
Requires-Dist: django >=4.0
